catas/__init__.py
catas/__main__.py
catas/cli.py
catas/count.py
catas/dbcan.py
catas/exitcodes.py
catas/external.py
catas/main.py
catas/matrix.py
catas/model.py
catas/parsers.py
catas/sanitise.py
catas/utils.py
catas/data/__init__.py
catas/data/hmmscan-parser.sh
catas/data/model_v10_20211001.npz
catas/data/model_v4_20200114.npz
catas/data/model_v4_20211001.npz
catas/data/model_v5_20200114.npz
catas/data/model_v5_20211001.npz
catas/data/model_v6_20200114.npz
catas/data/model_v6_20211001.npz
catas/data/model_v7_20200114.npz
catas/data/model_v7_20211001.npz
catas/data/model_v8_20200114.npz
catas/data/model_v8_20211001.npz
catas/data/model_v9_20211001.npz
catas/data/nomenclatures.json
catas/data/test_data.fasta
catas/data/test_v10/__init__.py
catas/data/test_v10/counts.tsv
catas/data/test_v10/hmmer_dbcan.tsv
catas/data/test_v10/hmmer_domtab.tsv
catas/data/test_v10/hmmer_text.txt
catas/data/test_v10/pca.tsv
catas/data/test_v10/rcd.tsv
catas/data/test_v4/__init__.py
catas/data/test_v4/counts.tsv
catas/data/test_v4/hmmer_dbcan.tsv
catas/data/test_v4/hmmer_domtab.tsv
catas/data/test_v4/hmmer_text.txt
catas/data/test_v4/pca.tsv
catas/data/test_v4/rcd.tsv
catas/data/test_v5/__init__.py
catas/data/test_v5/counts.tsv
catas/data/test_v5/hmmer_dbcan.tsv
catas/data/test_v5/hmmer_domtab.tsv
catas/data/test_v5/hmmer_text.txt
catas/data/test_v5/pca.tsv
catas/data/test_v5/rcd.tsv
catas/data/test_v6/__init__.py
catas/data/test_v6/counts.tsv
catas/data/test_v6/hmmer_dbcan.tsv
catas/data/test_v6/hmmer_domtab.tsv
catas/data/test_v6/hmmer_text.txt
catas/data/test_v6/pca.tsv
catas/data/test_v6/rcd.tsv
catas/data/test_v7/__init__.py
catas/data/test_v7/counts.tsv
catas/data/test_v7/hmmer_dbcan.tsv
catas/data/test_v7/hmmer_domtab.tsv
catas/data/test_v7/hmmer_text.txt
catas/data/test_v7/pca.tsv
catas/data/test_v7/rcd.tsv
catas/data/test_v8/__init__.py
catas/data/test_v8/counts.tsv
catas/data/test_v8/hmmer_dbcan.tsv
catas/data/test_v8/hmmer_domtab.tsv
catas/data/test_v8/hmmer_text.txt
catastrophy-0.1.0.dist-info/LICENSE
catastrophy-0.1.0.dist-info/METADATA
catastrophy-0.1.0.dist-info/WHEEL
catastrophy-0.1.0.dist-info/entry_points.txt
catastrophy-0.1.0.dist-info/top_level.txt
catastrophy-0.1.0.dist-info/RECORD
