Metadata-Version: 2.1
Name: catastrophy
Version: 0.1.0
Summary: A fungal trophy classifier based on CAZymes
Home-page: https://github.com/ccdmb/catastrophy
Author: Darcy Jones
Author-email: darcy.a.jones@curtin.edu.au
License: BSD
Keywords: fungi machine-learning bioinformatics
Classifier: Development Status :: 4 - Beta
Classifier: License :: OSI Approved :: BSD License
Classifier: Programming Language :: Python :: 3
Classifier: Programming Language :: Python :: 3.7
Classifier: Programming Language :: Python :: 3.8
Classifier: Programming Language :: Python :: 3.9
License-File: LICENSE
Requires-Dist: numpy (>=1.11.0)
Requires-Dist: biopython (>=1.70)
Requires-Dist: joblib
Requires-Dist: requests
Provides-Extra: dev
Requires-Dist: check-manifest ; extra == 'dev'
Requires-Dist: mypy ; extra == 'dev'
Requires-Dist: scipy ; extra == 'dev'
Requires-Dist: scikit-learn ; extra == 'dev'
Requires-Dist: jupyter ; extra == 'dev'
Requires-Dist: matplotlib ; extra == 'dev'
Requires-Dist: seaborn ; extra == 'dev'
Provides-Extra: test
Requires-Dist: coverage ; extra == 'test'
Requires-Dist: pytest ; extra == 'test'
Requires-Dist: mypy ; extra == 'test'
Requires-Dist: types-requests ; extra == 'test'
